fastq2folder/__init__.py
fastq2folder/fastq2folder.py
fastq2folder-1.0.7.dist-info/METADATA
fastq2folder-1.0.7.dist-info/WHEEL
fastq2folder-1.0.7.dist-info/licenses/LICENSE
fastq2folder-1.0.7.dist-info/RECORD
