Metadata-Version: 2.1
Name: fastq2folder
Version: 1.0.7
Summary: Script to process fastq files before epi2me analysis
Project-URL: Homepage, https://github.com/pypa/sampleproject
Project-URL: Bug Tracker, https://github.com/pypa/sampleproject/issues
Author-email: Elizabeth Gardner <egar18111@gmail.com>
License-File: LICENSE
Classifier: License :: OSI Approved :: MIT License
Classifier: Operating System :: OS Independent
Classifier: Programming Language :: Python :: 3
Requires-Python: >=3.7
Requires-Dist: bio>=1.5.9
Requires-Dist: matplotlib>=3.6.2
Requires-Dist: numpy>=1.22.4
Requires-Dist: pandas>=1.4.2
Requires-Dist: scipy>=1.10.1
Requires-Dist: seaborn>=0.12.2
